lib_ordrsp/__init__.py
lib_ordrsp/ordrsp.py
lib_ordrsp-0.0.7.dist-info/METADATA
lib_ordrsp-0.0.7.dist-info/WHEEL
lib_ordrsp-0.0.7.dist-info/RECORD
