Metadata-Version: 2.4
Name: lib-ordrsp
Version: 0.0.7
Summary: 
Author: Nathan Blum
Author-email: n.blum@student.tudelft.nl
Requires-Python: >=3.10
Classifier: Programming Language :: Python :: 3
Classifier: Programming Language :: Python :: 3.10
Classifier: Programming Language :: Python :: 3.11
Classifier: Programming Language :: Python :: 3.12
Classifier: Programming Language :: Python :: 3.13
Classifier: Programming Language :: Python :: 3.14
Requires-Dist: lib-sap (>=0.0.7,<0.0.8)
Requires-Dist: numpy (==2.2.6)
